[
{"CreatedAt":"Fri Mar 13 17:18:40 +0000 2015","Text":"また冷えるの・・・","StatusId":"576432199995535360","UserName":"Gada / ymtszw","UserProfileImageUrl":"https://pbs.twimg.com/profile_images/1520432647868391430/4b2AUYjC_normal.jpg","Retweet":"FALSE"}
,
{"CreatedAt":"Fri Mar 13 22:31:06 +0000 2015","Text":"ダービー兄終わったらホル・ホースとボインゴ、ペットショップ、ダービー弟、ヴァニラ・アイスでDIOか","StatusId":"576510826107969536","UserName":"Gada / ymtszw","UserProfileImageUrl":"https://pbs.twimg.com/profile_images/1520432647868391430/4b2AUYjC_normal.jpg","Retweet":"FALSE"}
]
