[
{"CreatedAt":"Tue Sep 26 12:42:50 +0000 2017","Text":"@bicycle_panda ムハンマドはまだいいよ、自然な流れだから\n\nイスラムからはボンバーマンとか書いてるやつ、死んだぞ","StatusId":"912658723675312128","UserName":"Gada / ymtszw","UserProfileImageUrl":"https://pbs.twimg.com/profile_images/1520432647868391430/4b2AUYjC_normal.jpg","InReplyToStatusId":"912654644010086400","InReplyToUserId":"7008482","Retweet":"FALSE"}
,
{"CreatedAt":"Tue Sep 26 12:52:29 +0000 2017","Text":"【MLB】田澤の偉業を地元紙が特集　ハイチュウで米国に「雇用を生み出した」 #SmartNews \n\nハイチュウ田澤 https://t.co/KC29PUJDpF","StatusId":"912661151283953665","UserName":"Gada / ymtszw","UserProfileImageUrl":"https://pbs.twimg.com/profile_images/1520432647868391430/4b2AUYjC_normal.jpg","EntitiesUrlsUrls":"https://t.co/KC29PUJDpF","EntitiesUrlsExpandedUrls":"https://www.baseballchannel.jp/mlb/39519/","Retweet":"FALSE"}
,
{"CreatedAt":"Tue Sep 26 12:53:29 +0000 2017","Text":"10,000本目は中井か。。。","StatusId":"912661404225695744","UserName":"Gada / ymtszw","UserProfileImageUrl":"https://pbs.twimg.com/profile_images/1520432647868391430/4b2AUYjC_normal.jpg","Retweet":"FALSE"}
,
{"CreatedAt":"Tue Sep 26 13:28:44 +0000 2017","Text":"Evo-Devo (Despacito Biology Parody) | A Capella Science https://t.co/WDkt4nxgrI @YouTubeさんから","StatusId":"912670272108453888","UserName":"Gada / ymtszw","UserProfileImageUrl":"https://pbs.twimg.com/profile_images/1520432647868391430/4b2AUYjC_normal.jpg","EntitiesUrlsUrls":"https://t.co/WDkt4nxgrI","EntitiesUrlsExpandedUrls":"https://youtu.be/ydqReeTV_vk","Retweet":"FALSE"}
,
{"CreatedAt":"Tue Sep 26 14:02:42 +0000 2017","Text":"Follower装備は、「カウンター強化+40％、同+30%、無条件成功率+25%」ってのが実用的には一番便利な気がするが（大抵の場合なんかカウンターを当てるから）、カウンター外れてる場合を考えると「無条件+25%、同+20%、カウンター+40%」も良さそうで迷う","StatusId":"912678820167041024","UserName":"Gada / ymtszw","UserProfileImageUrl":"https://pbs.twimg.com/profile_images/1520432647868391430/4b2AUYjC_normal.jpg","Retweet":"FALSE"}
,
{"CreatedAt":"Tue Sep 26 14:04:30 +0000 2017","Text":"Raidの開く頃には新しいFollowerレジェとかも出るのだろうか","StatusId":"912679276620562433","UserName":"Gada / ymtszw","UserProfileImageUrl":"https://pbs.twimg.com/profile_images/1520432647868391430/4b2AUYjC_normal.jpg","InReplyToStatusId":"912678820167041024","InReplyToUserId":"352840258","Retweet":"FALSE"}
,
{"CreatedAt":"Tue Sep 26 14:06:08 +0000 2017","Text":"現状とりあえずLucky Doodad（無条件+10%）は卒業できたが、無条件+15%（レジェ含む）はまだ卒業できてないやつがいる","StatusId":"912679686521491458","UserName":"Gada / ymtszw","UserProfileImageUrl":"https://pbs.twimg.com/profile_images/1520432647868391430/4b2AUYjC_normal.jpg","InReplyToStatusId":"912679276620562433","InReplyToUserId":"352840258","Retweet":"FALSE"}
,
{"CreatedAt":"Tue Sep 26 14:15:46 +0000 2017","Text":"クエスト進めるとAntorun Wastesで新しいTroop雇えるようになって、今度のはたぶんMinionカウンター+75%だから、それを合わせるとレアtroopが足りてる限りはfollowerx1，troopx1で200%余裕になるんで、カウンター装備x2は冗長かも","StatusId":"912682108992155649","UserName":"Gada / ymtszw","UserProfileImageUrl":"https://pbs.twimg.com/profile_images/1520432647868391430/4b2AUYjC_normal.jpg","InReplyToStatusId":"912679686521491458","InReplyToUserId":"352840258","Retweet":"FALSE"}
]
