[
{"CreatedAt":"Tue Jun 21 15:18:01 +0000 2022","Text":"RT @voluntas: Cloudflare outage on June 21, 2022 https://t.co/zegXt9hGMa 今日の障害、解説記事きた！","StatusId":"1539266393341714432","UserName":"Gada / ymtszw","UserProfileImageUrl":"https://pbs.twimg.com/profile_images/1520432647868391430/4b2AUYjC_normal.jpg","Retweet":"TRUE","RetweetedStatusFullText":"Cloudflare outage on June 21, 2022 https://t.co/zegXt9hGMa 今日の障害、解説記事きた！","RetweetedStatusId":"1539266393341714432","RetweetedStatusUserName":"V","RetweetedStatusUserProfileImageUrl":"https://abs.twimg.com/sticky/default_profile_images/default_profile_200x200.png"}
,
{"CreatedAt":"Tue Jun 21 17:24:34 +0000 2022","Text":"&gt; *World of Warcraft®: Dragonflight will be available on or before December 31, 2022.\n\nそうかなあ？そうはならんのちゃうか #wowjp #ut_wow https://t.co/RxErG9mgKY","StatusId":"1539298243594813440","UserName":"Gada / ymtszw","UserProfileImageUrl":"https://pbs.twimg.com/profile_images/1520432647868391430/4b2AUYjC_normal.jpg","Retweet":"FALSE"}
,
{"CreatedAt":"Wed Jun 22 12:19:20 +0000 2022","Text":"RT @feenal: OMORIのRTAは未プレイであればRTAでも見ないほうがいいですよ　走者には悪いけど走者も多分そう思ってるのでは…","StatusId":"1539583814892421120","UserName":"Gada / ymtszw","UserProfileImageUrl":"https://pbs.twimg.com/profile_images/1520432647868391430/4b2AUYjC_normal.jpg","Retweet":"TRUE","RetweetedStatusFullText":"OMORIのRTAは未プレイであればRTAでも見ないほうがいいですよ　走者には悪いけど走者も多分そう思ってるのでは…","RetweetedStatusId":"1539583814892421120","RetweetedStatusUserName":"Aki","RetweetedStatusUserProfileImageUrl":"https://abs.twimg.com/sticky/default_profile_images/default_profile_200x200.png"}
]
