[
{"CreatedAt":"Thu Aug 08 18:56:34 +0000 2019","Text":"RT @farbodsaraf: Teaching chemistry using augmented reality https://t.co/rH9HNUjp57","StatusId":"1159538911191789568","UserName":"Gada / ymtszw","UserProfileImageUrl":"https://pbs.twimg.com/profile_images/1520432647868391430/4b2AUYjC_normal.jpg","Retweet":"TRUE","RetweetedStatusFullText":"Teaching chemistry using augmented reality https://t.co/rH9HNUjp57","RetweetedStatusId":"1159538911191789568","RetweetedStatusUserName":"Farbod Saraf","RetweetedStatusUserProfileImageUrl":"https://abs.twimg.com/sticky/default_profile_images/default_profile_200x200.png"}
,
{"CreatedAt":"Thu Aug 08 21:41:43 +0000 2019","Text":"RT @minamijoyo: 長年放置されてたawscliの公式Dockerイメージがない問題、ついに中の人がいま準備中とコメントしたぞ。 https://t.co/8w0TN2cDBA","StatusId":"1159580475213533184","UserName":"Gada / ymtszw","UserProfileImageUrl":"https://pbs.twimg.com/profile_images/1520432647868391430/4b2AUYjC_normal.jpg","Retweet":"TRUE","RetweetedStatusFullText":"長年放置されてたawscliの公式Dockerイメージがない問題、ついに中の人がいま準備中とコメントしたぞ。 https://t.co/8w0TN2cDBA","RetweetedStatusId":"1159580475213533184","RetweetedStatusUserName":"城陽人","RetweetedStatusUserProfileImageUrl":"https://abs.twimg.com/sticky/default_profile_images/default_profile_200x200.png"}
,
{"CreatedAt":"Thu Aug 08 23:00:45 +0000 2019","Text":"awscli入ったイメージ、deploy速度短縮に十秒くらいは寄与してくれそう","StatusId":"1159600364888313856","UserName":"Gada / ymtszw","UserProfileImageUrl":"https://pbs.twimg.com/profile_images/1520432647868391430/4b2AUYjC_normal.jpg","Retweet":"FALSE"}
,
{"CreatedAt":"Fri Aug 09 03:41:31 +0000 2019","Text":"飯山、仙台育英引いちゃったのか。","StatusId":"1159671019574923264","UserName":"Gada / ymtszw","UserProfileImageUrl":"https://pbs.twimg.com/profile_images/1520432647868391430/4b2AUYjC_normal.jpg","Retweet":"FALSE"}
,
{"CreatedAt":"Fri Aug 09 09:35:18 +0000 2019","Text":"誰もがこれを考えるので,\nhttps://t.co/OMu7kWiSL7\nとか、\nhttps://t.co/iCiUTNvFTP\nとかあるけど、どれもあまりgrowthに至ってないイメージがある。自分でも少し作ってみたりしたけど、各社機能追加が早いし、3rd partyクライアントは締め出しがちだし、群雄割拠時代になってしまった https://t.co/JTeM8erp46","StatusId":"1159760050639892480","UserName":"Gada / ymtszw","UserProfileImageUrl":"https://pbs.twimg.com/profile_images/1520432647868391430/4b2AUYjC_normal.jpg","Retweet":"FALSE"}
,
{"CreatedAt":"Fri Aug 09 09:59:27 +0000 2019","Text":"awscliの--queryオプションに切り替えて見ようかと調べたけど、やっぱjqのほうが融通が利く感ある","StatusId":"1159766132179398658","UserName":"Gada / ymtszw","UserProfileImageUrl":"https://pbs.twimg.com/profile_images/1520432647868391430/4b2AUYjC_normal.jpg","Retweet":"FALSE"}
]
