[
{"CreatedAt":"Mon Aug 31 11:57:16 +0000 2015","Text":"フリクリにリメイクの余地があると踏んでるのか。。 https://t.co/I5vOtcWmB8","StatusId":"638319642960793600","UserName":"Gada / ymtszw","UserProfileImageUrl":"https://pbs.twimg.com/profile_images/1520432647868391430/4b2AUYjC_normal.jpg","EntitiesUrlsUrls":"https://t.co/I5vOtcWmB8","EntitiesUrlsExpandedUrls":"https://twitter.com/geijingeijin/status/638253846624534528","Retweet":"FALSE"}
,
{"CreatedAt":"Mon Aug 31 13:58:11 +0000 2015","Text":"熟練艦載機で3-5上コースが楽になったな。","StatusId":"638350071113887744","UserName":"Gada / ymtszw","UserProfileImageUrl":"https://pbs.twimg.com/profile_images/1520432647868391430/4b2AUYjC_normal.jpg","Retweet":"FALSE"}
,
{"CreatedAt":"Mon Aug 31 13:58:39 +0000 2015","Text":"てことは多分4－5も楽になっているけどまあいいや","StatusId":"638350187312861185","UserName":"Gada / ymtszw","UserProfileImageUrl":"https://pbs.twimg.com/profile_images/1520432647868391430/4b2AUYjC_normal.jpg","Retweet":"FALSE"}
]
