[
{"CreatedAt":"Wed Feb 28 16:51:39 +0000 2018","Text":"window.screen.width(Elm内ではInt)をもとにresponsiveに計算して求めるべき値(これもInt)を取る関数に、間違ってwidthそれ自体が入力されていたため、DOMが大量生成されるという酷いバグを仕込んだ。ぼくはすべてのIntやStringをTagged Typeにしたいという強い欲求に駆られた","StatusId":"968891457183481857","UserName":"Gada / ymtszw","UserProfileImageUrl":"https://pbs.twimg.com/profile_images/1520432647868391430/4b2AUYjC_normal.jpg","Retweet":"FALSE"}
,
{"CreatedAt":"Wed Feb 28 17:31:46 +0000 2018","Text":"RT @rstephens: Jesus, just merge ALL Google \"chat\" apps back into a single service called Google Talk (Voice, Hangouts, also, duo, blah bla…","StatusId":"968901554546794496","UserName":"Gada / ymtszw","UserProfileImageUrl":"https://pbs.twimg.com/profile_images/1520432647868391430/4b2AUYjC_normal.jpg","Retweet":"TRUE","RetweetedStatusFullText":"Jesus, just merge ALL Google \"chat\" apps back into a single service called Google Talk (Voice, Hangouts, also, duo, blah bla…","RetweetedStatusId":"968901554546794496","RetweetedStatusUserName":"Robert Stephens","RetweetedStatusUserProfileImageUrl":"https://res.cloudinary.com/du9b7ybxy/image/twitter_name/h_20,w_20,d_default_twitter_avatar.jpg/rstephens.jpg"}
,
{"CreatedAt":"Wed Feb 28 18:42:15 +0000 2018","Text":"最近おもろない漫画を結構買ってしまってて良くない気がする","StatusId":"968919292862390272","UserName":"Gada / ymtszw","UserProfileImageUrl":"https://pbs.twimg.com/profile_images/1520432647868391430/4b2AUYjC_normal.jpg","Retweet":"FALSE"}
,
{"CreatedAt":"Thu Mar 01 02:27:03 +0000 2018","Text":"クラシック流れてる日比谷線に乗った。\n電車動いてる間走行音で何も聞こえない","StatusId":"969036262966308864","UserName":"Gada / ymtszw","UserProfileImageUrl":"https://pbs.twimg.com/profile_images/1520432647868391430/4b2AUYjC_normal.jpg","Retweet":"FALSE"}
,
{"CreatedAt":"Thu Mar 01 04:08:19 +0000 2018","Text":"RT @itlweb: Nintendo Switch™用ゲームソフト HANDY麻雀 の公式サイトをオープンしました。\nhttps://t.co/z2YNxEOsIg https://t.co/ffLpl6MbPx","StatusId":"969061746857074688","UserName":"Gada / ymtszw","UserProfileImageUrl":"https://pbs.twimg.com/profile_images/1520432647868391430/4b2AUYjC_normal.jpg","EntitiesUrlsUrls":"https://t.co/z2YNxEOsIg","EntitiesUrlsExpandedUrls":"https://itl.ne.jp/news.html#d180226","ExtendedEntitiesMediaUrls":"https://t.co/ffLpl6MbPx","ExtendedEntitiesMediaSourceUrls":"https://pbs.twimg.com/media/DW791sfVAAIoiOa.jpg","ExtendedEntitiesMediaTypes":"photo","ExtendedEntitiesMediaExpandedUrls":"https://twitter.com/itlweb/status/967990134636294144/photo/1","Retweet":"TRUE","RetweetedStatusFullText":"Nintendo Switch™用ゲームソフト HANDY麻雀 の公式サイトをオープンしました。\nhttps://t.co/z2YNxEOsIg https://t.co/ffLpl6MbPx","RetweetedStatusId":"969061746857074688","RetweetedStatusUserName":"株式会社アイティーエル","RetweetedStatusUserProfileImageUrl":"https://res.cloudinary.com/du9b7ybxy/image/twitter_name/h_20,w_20,d_default_twitter_avatar.jpg/itlweb.jpg"}
,
{"CreatedAt":"Thu Mar 01 04:09:07 +0000 2018","Text":"でもこのUI（？）、海戦ゲームみたいでちょっと楽しい感覚あると思う","StatusId":"969061947734859776","UserName":"Gada / ymtszw","UserProfileImageUrl":"https://pbs.twimg.com/profile_images/1520432647868391430/4b2AUYjC_normal.jpg","Retweet":"FALSE"}
,
{"CreatedAt":"Thu Mar 01 05:55:13 +0000 2018","Text":"iTerm2のcopy modeいままであんまり使ってなかったけど、改めて使ってみると普通に便利だった。使わない理由ないな","StatusId":"969088648120430592","UserName":"Gada / ymtszw","UserProfileImageUrl":"https://pbs.twimg.com/profile_images/1520432647868391430/4b2AUYjC_normal.jpg","Retweet":"FALSE"}
,
{"CreatedAt":"Thu Mar 01 06:36:41 +0000 2018","Text":"RT @Niku8132: ポプテピピックのレモンなめたときの顔大好きなので\nポプテ × wowのorcとtrollで描きますた https://t.co/9jn4weH8nE","StatusId":"969099084224081920","UserName":"Gada / ymtszw","UserProfileImageUrl":"https://pbs.twimg.com/profile_images/1520432647868391430/4b2AUYjC_normal.jpg","ExtendedEntitiesMediaUrls":"https://t.co/9jn4weH8nE","ExtendedEntitiesMediaSourceUrls":"https://pbs.twimg.com/media/DXLXtTIUQAAd59H.jpg","ExtendedEntitiesMediaTypes":"photo","ExtendedEntitiesMediaExpandedUrls":"https://twitter.com/Niku8132/status/969074231597150208/photo/1","Retweet":"TRUE","RetweetedStatusFullText":"ポプテピピックのレモンなめたときの顔大好きなので\nポプテ × wowのorcとtrollで描きますた https://t.co/9jn4weH8nE","RetweetedStatusId":"969099084224081920","RetweetedStatusUserName":"長内佑介／にく","RetweetedStatusUserProfileImageUrl":"https://res.cloudinary.com/du9b7ybxy/image/twitter_name/h_20,w_20,d_default_twitter_avatar.jpg/Niku8132.jpg"}
,
{"CreatedAt":"Thu Mar 01 13:30:08 +0000 2018","Text":"RT @miyamo_madoka: Rustやってる感想としてはElm簡単です","StatusId":"969203134412156928","UserName":"Gada / ymtszw","UserProfileImageUrl":"https://pbs.twimg.com/profile_images/1520432647868391430/4b2AUYjC_normal.jpg","Retweet":"TRUE","RetweetedStatusFullText":"Rustやってる感想としてはElm簡単です","RetweetedStatusId":"969203134412156928","RetweetedStatusUserName":"みやも","RetweetedStatusUserProfileImageUrl":"https://res.cloudinary.com/du9b7ybxy/image/twitter_name/h_20,w_20,d_default_twitter_avatar.jpg/miyamo_madoka.jpg"}
,
{"CreatedAt":"Thu Mar 01 14:00:33 +0000 2018","Text":"Diablo率上がってないか？やっぱなんだかんだでみんな好きなんスねーってことなのかそれとも兄貴の影響力が甚大なのか","StatusId":"969210787779690501","UserName":"Gada / ymtszw","UserProfileImageUrl":"https://pbs.twimg.com/profile_images/1520432647868391430/4b2AUYjC_normal.jpg","Retweet":"FALSE"}
]
