[
{"CreatedAt":"Tue Mar 27 15:57:16 +0000 2018","Text":"RT @WCHLChapelboro: @lebrownlow When Tweetdeck goes down and we have to resort to using normal Twitter https://t.co/bKH6IMbrUq","StatusId":"978662243867873281","UserName":"Gada / ymtszw","UserProfileImageUrl":"https://pbs.twimg.com/profile_images/1520432647868391430/4b2AUYjC_normal.jpg","ExtendedEntitiesMediaUrls":"https://t.co/bKH6IMbrUq","ExtendedEntitiesMediaSourceUrls":"https://pbs.twimg.com/tweet_video_thumb/DZTn0XrX0AAV9id.jpg","ExtendedEntitiesMediaTypes":"animated_gif","ExtendedEntitiesMediaExpandedUrls":"https://twitter.com/WCHLChapelboro/status/978661977223462913/photo/1","Retweet":"TRUE","RetweetedStatusFullText":"@lebrownlow When Tweetdeck goes down and we have to resort to using normal Twitter https://t.co/bKH6IMbrUq","RetweetedStatusId":"978662243867873281","RetweetedStatusUserName":"WCHL & Chapelboro","RetweetedStatusUserProfileImageUrl":"https://abs.twimg.com/sticky/default_profile_images/default_profile_200x200.png"}
,
{"CreatedAt":"Tue Mar 27 16:55:46 +0000 2018","Text":"南極はオリジナルだから最後まで目が離せなかったし、しかも最後までちゃんと面白かったから素晴らしかった","StatusId":"978676966755725312","UserName":"Gada / ymtszw","UserProfileImageUrl":"https://pbs.twimg.com/profile_images/1520432647868391430/4b2AUYjC_normal.jpg","Retweet":"FALSE"}
,
{"CreatedAt":"Tue Mar 27 17:03:19 +0000 2018","Text":"原作付きは今だと1話見ておっと思ったら即原作全部買っちゃうことが多いから、その後アニメの方は惰性で見る感じになるorいいやっってなっちゃうのはちょっと考えものだ。","StatusId":"978678867840851968","UserName":"Gada / ymtszw","UserProfileImageUrl":"https://pbs.twimg.com/profile_images/1520432647868391430/4b2AUYjC_normal.jpg","InReplyToStatusId":"978676966755725312","InReplyToUserId":"352840258","Retweet":"FALSE"}
,
{"CreatedAt":"Tue Mar 27 18:38:15 +0000 2018","Text":"Effect Managerについてちらっと読もうとしたらRandom.elmのmaster実装にPCG法という疑似乱数生成器が使われてることを知り、調べてみたら学生の時読んだ本でイケてるんだぜ～と書かれていたメルセンヌ・ツイスタよりイケてると主張されていて、知識の陳腐化に泣く","StatusId":"978702759246508033","UserName":"Gada / ymtszw","UserProfileImageUrl":"https://pbs.twimg.com/profile_images/1520432647868391430/4b2AUYjC_normal.jpg","Retweet":"FALSE"}
,
{"CreatedAt":"Tue Mar 27 18:39:18 +0000 2018","Text":"メルセンヌ・ツイスタ、名前がかっこいいから好きだったのに。。","StatusId":"978703020136411136","UserName":"Gada / ymtszw","UserProfileImageUrl":"https://pbs.twimg.com/profile_images/1520432647868391430/4b2AUYjC_normal.jpg","InReplyToStatusId":"978702759246508033","InReplyToUserId":"352840258","Retweet":"FALSE"}
,
{"CreatedAt":"Tue Mar 27 19:11:50 +0000 2018","Text":"Party Tricks | PCG, A Better Random Number Generator https://t.co/5oGVcwIJmp\n\nおもろい","StatusId":"978711208642584576","UserName":"Gada / ymtszw","UserProfileImageUrl":"https://pbs.twimg.com/profile_images/1520432647868391430/4b2AUYjC_normal.jpg","EntitiesUrlsUrls":"https://t.co/5oGVcwIJmp","EntitiesUrlsExpandedUrls":"http://www.pcg-random.org/party-tricks.html","Retweet":"FALSE"}
,
{"CreatedAt":"Wed Mar 28 04:32:56 +0000 2018","Text":"@bols_blue こないだ言ってたツイート発掘したけど、「欲しい機能」ってだけですでにあるわけじゃなかった https://t.co/RHsvb3BcWa","StatusId":"978852413141606400","UserName":"Gada / ymtszw","UserProfileImageUrl":"https://pbs.twimg.com/profile_images/1520432647868391430/4b2AUYjC_normal.jpg","InReplyToUserId":"47539662","EntitiesUrlsUrls":"https://t.co/RHsvb3BcWa","EntitiesUrlsExpandedUrls":"https://twitter.com/tomozh/status/976092377570934785","Retweet":"FALSE"}
,
{"CreatedAt":"Wed Mar 28 04:58:04 +0000 2018","Text":"RT @blackenedgold: 形式手法とテスト、そして、その先について - D3.pdf\nhttps://t.co/IFdvbAbfir","StatusId":"978858738680565760","UserName":"Gada / ymtszw","UserProfileImageUrl":"https://pbs.twimg.com/profile_images/1520432647868391430/4b2AUYjC_normal.jpg","EntitiesUrlsUrls":"https://t.co/IFdvbAbfir","EntitiesUrlsExpandedUrls":"http://jasst.jp/symposium/jasst17tokyo/pdf/D3.pdf","Retweet":"TRUE","RetweetedStatusFullText":"形式手法とテスト、そして、その先について - D3.pdf\nhttps://t.co/IFdvbAbfir","RetweetedStatusId":"978858738680565760","RetweetedStatusUserName":"κeen","RetweetedStatusUserProfileImageUrl":"https://abs.twimg.com/sticky/default_profile_images/default_profile_200x200.png"}
,
{"CreatedAt":"Wed Mar 28 08:25:06 +0000 2018","Text":"RT @jinjor: SVG でしか出来ないと思ってたやつ CSS で出来てしまって悔しい。愛人に浮気したけど最終的に妻のもとに戻ってくる的な。","StatusId":"978910840278548481","UserName":"Gada / ymtszw","UserProfileImageUrl":"https://pbs.twimg.com/profile_images/1520432647868391430/4b2AUYjC_normal.jpg","Retweet":"TRUE","RetweetedStatusFullText":"SVG でしか出来ないと思ってたやつ CSS で出来てしまって悔しい。愛人に浮気したけど最終的に妻のもとに戻ってくる的な。","RetweetedStatusId":"978910840278548481","RetweetedStatusUserName":"Yosuke Torii / ジンジャー","RetweetedStatusUserProfileImageUrl":"https://abs.twimg.com/sticky/default_profile_images/default_profile_200x200.png"}
,
{"CreatedAt":"Wed Mar 28 13:35:07 +0000 2018","Text":"RT @pankona: public boolean isBoolean = false;\n\n思い出すたびに言葉で言い表せない不思議な感情が蘇る","StatusId":"978988857885536258","UserName":"Gada / ymtszw","UserProfileImageUrl":"https://pbs.twimg.com/profile_images/1520432647868391430/4b2AUYjC_normal.jpg","Retweet":"TRUE","RetweetedStatusFullText":"public boolean isBoolean = false;\n\n思い出すたびに言葉で言い表せない不思議な感情が蘇る","RetweetedStatusId":"978988857885536258","RetweetedStatusUserName":"パン粉","RetweetedStatusUserProfileImageUrl":"https://abs.twimg.com/sticky/default_profile_images/default_profile_200x200.png"}
,
{"CreatedAt":"Wed Mar 28 13:57:32 +0000 2018","Text":"やわらかスピリッツ - 人魚姫のごめんねごはん | 第23話 https://t.co/H4jtDXJwUE\n\nごめんねごはんは面白いし、流行る気配も少しずつ感じてきている","StatusId":"978994500017184769","UserName":"Gada / ymtszw","UserProfileImageUrl":"https://pbs.twimg.com/profile_images/1520432647868391430/4b2AUYjC_normal.jpg","EntitiesUrlsUrls":"https://t.co/H4jtDXJwUE","EntitiesUrlsExpandedUrls":"http://yawaspi.com/gomennegohan/comic/033_001.html","Retweet":"FALSE"}
]
