[
{"CreatedAt":"Sun Aug 14 08:02:03 +0000 2016","Text":"Bio4のショットガンバグ状態で水上オートバイ乗るやつ思い出す","StatusId":"764733812756459520","UserName":"Gada / ymtszw","UserProfileImageUrl":"https://pbs.twimg.com/profile_images/1520432647868391430/4b2AUYjC_normal.jpg","Retweet":"FALSE"}
,
{"CreatedAt":"Sun Aug 14 07:38:38 +0000 2016","Text":"RT @dakfan: Dragonball Z easter egg in Shattrath https://t.co/PG4eivD1ct","StatusId":"764727917624434688","UserName":"Gada / ymtszw","UserProfileImageUrl":"https://pbs.twimg.com/profile_images/1520432647868391430/4b2AUYjC_normal.jpg","Retweet":"TRUE","RetweetedStatusFullText":"Dragonball Z easter egg in Shattrath https://t.co/PG4eivD1ct","RetweetedStatusId":"764727917624434688","RetweetedStatusUserName":"kowamote 関西コミティア67 5/21","RetweetedStatusUserProfileImageUrl":"https://abs.twimg.com/sticky/default_profile_images/default_profile_200x200.png"}
,
{"CreatedAt":"Sun Aug 14 05:43:02 +0000 2016","Text":"@kazaxchino 原本消しちゃったし、まあいいや","StatusId":"764698828926652421","UserName":"Gada / ymtszw","UserProfileImageUrl":"https://pbs.twimg.com/profile_images/1520432647868391430/4b2AUYjC_normal.jpg","Retweet":"FALSE"}
,
{"CreatedAt":"Sun Aug 14 05:02:30 +0000 2016","Text":"ログが読めるようになるまでこんなに時間かかったっけな。。","StatusId":"764688627146166272","UserName":"Gada / ymtszw","UserProfileImageUrl":"https://pbs.twimg.com/profile_images/1520432647868391430/4b2AUYjC_normal.jpg","Retweet":"FALSE"}
,
{"CreatedAt":"Sun Aug 14 04:58:50 +0000 2016","Text":"@twitte_RS あれ画像じゃなくてCSSで作ってるからね","StatusId":"764687704139272193","UserName":"Gada / ymtszw","UserProfileImageUrl":"https://pbs.twimg.com/profile_images/1520432647868391430/4b2AUYjC_normal.jpg","Retweet":"FALSE"}
,
{"CreatedAt":"Sun Aug 14 04:38:35 +0000 2016","Text":"昨夜は泥縄でいろいろ準備してもらいましたが、Discordと幾つかAddonは必須なので準備しておいて下さい。 https://t.co/Xwxr8ambT3 #ut_wow","StatusId":"764682607242063872","UserName":"Gada / ymtszw","UserProfileImageUrl":"https://pbs.twimg.com/profile_images/1520432647868391430/4b2AUYjC_normal.jpg","Retweet":"FALSE"}
,
{"CreatedAt":"Sun Aug 14 04:37:11 +0000 2016","Text":"昨夜のログ、上げておきました。Warcraft Logsに上げていくのでお役立て下さい。 https://t.co/hebwhWBTxd #ut_wow","StatusId":"764682254836649984","UserName":"Gada / ymtszw","UserProfileImageUrl":"https://pbs.twimg.com/profile_images/1520432647868391430/4b2AUYjC_normal.jpg","Retweet":"FALSE"}
,
{"CreatedAt":"Sun Aug 14 03:54:01 +0000 2016","Text":"RT @NeverThatKid: OH LETS BREAK IT DOWN  https://t.co/AQ4MKrYQ63","StatusId":"764671393212485632","UserName":"Gada / ymtszw","UserProfileImageUrl":"https://pbs.twimg.com/profile_images/1520432647868391430/4b2AUYjC_normal.jpg","Retweet":"TRUE","RetweetedStatusFullText":"OH LETS BREAK IT DOWN  https://t.co/AQ4MKrYQ63","RetweetedStatusId":"764671393212485632","RetweetedStatusUserName":"checkmate | 🏠","RetweetedStatusUserProfileImageUrl":"https://abs.twimg.com/sticky/default_profile_images/default_profile_200x200.png"}
,
{"CreatedAt":"Sun Aug 14 03:17:54 +0000 2016","Text":"@hal_tvvitter WarspiteはE4クリア","StatusId":"764662303358722048","UserName":"Gada / ymtszw","UserProfileImageUrl":"https://pbs.twimg.com/profile_images/1520432647868391430/4b2AUYjC_normal.jpg","Retweet":"FALSE"}
,
{"CreatedAt":"Sun Aug 14 03:15:43 +0000 2016","Text":"旧シーズンPvP装備の購入方法の変更 | Ultimate Triage https://t.co/rzSCV2UzTC","StatusId":"764661753552646145","UserName":"Gada / ymtszw","UserProfileImageUrl":"https://pbs.twimg.com/profile_images/1520432647868391430/4b2AUYjC_normal.jpg","Retweet":"FALSE"}
,
{"CreatedAt":"Sat Aug 13 15:17:22 +0000 2016","Text":"久々RaidでしたがHeroicで6/13やれました。Healer/Ranged募集中。 #ut_wow","StatusId":"764480975833223168","UserName":"Gada / ymtszw","UserProfileImageUrl":"https://pbs.twimg.com/profile_images/1520432647868391430/4b2AUYjC_normal.jpg","Retweet":"FALSE"}
,
{"CreatedAt":"Sat Aug 13 15:08:04 +0000 2016","Text":"@hal_tvvitter びっくりするほどキーがなくて、Tankに変えた","StatusId":"764478635159937024","UserName":"Gada / ymtszw","UserProfileImageUrl":"https://pbs.twimg.com/profile_images/1520432647868391430/4b2AUYjC_normal.jpg","Retweet":"FALSE"}
]
