[
{"CreatedAt":"Wed Aug 17 15:03:41 +0000 2022","Text":"RT @c18t: UWPを信じて裏切られ、Xamarin.Formを信じて裏切られ、今度は.Net MAUIを信じようとしています","StatusId":"1559918895741317121","UserName":"Gada / ymtszw","UserProfileImageUrl":"https://pbs.twimg.com/profile_images/1520432647868391430/4b2AUYjC_normal.jpg","Retweet":"TRUE","RetweetedStatusFullText":"UWPを信じて裏切られ、Xamarin.Formを信じて裏切られ、今度は.Net MAUIを信じようとしています","RetweetedStatusId":"1559918895741317121","RetweetedStatusUserName":"ムャー姉","RetweetedStatusUserProfileImageUrl":"https://abs.twimg.com/sticky/default_profile_images/default_profile_200x200.png"}
,
{"CreatedAt":"Wed Aug 17 15:44:27 +0000 2022","Text":"RT @tnacigam: 最近は GitHub でプルリクをマージするときに squash するのが流行り[要出典]だけど、それって実質的に Subversion の流儀に先祖返りしてるってことなんやなぁと","StatusId":"1559929156393021440","UserName":"Gada / ymtszw","UserProfileImageUrl":"https://pbs.twimg.com/profile_images/1520432647868391430/4b2AUYjC_normal.jpg","Retweet":"TRUE","RetweetedStatusFullText":"最近は GitHub でプルリクをマージするときに squash するのが流行り[要出典]だけど、それって実質的に Subversion の流儀に先祖返りしてるってことなんやなぁと","RetweetedStatusId":"1559929156393021440","RetweetedStatusUserName":"まじかんと","RetweetedStatusUserProfileImageUrl":"https://abs.twimg.com/sticky/default_profile_images/default_profile_200x200.png"}
,
{"CreatedAt":"Wed Aug 17 16:01:11 +0000 2022","Text":"RT @tnacigam: 結局のところ、コミットグラフといふ概念は人類には早すぎたといふことなのか?","StatusId":"1559933368963579904","UserName":"Gada / ymtszw","UserProfileImageUrl":"https://pbs.twimg.com/profile_images/1520432647868391430/4b2AUYjC_normal.jpg","Retweet":"TRUE","RetweetedStatusFullText":"結局のところ、コミットグラフといふ概念は人類には早すぎたといふことなのか?","RetweetedStatusId":"1559933368963579904","RetweetedStatusUserName":"まじかんと","RetweetedStatusUserProfileImageUrl":"https://abs.twimg.com/sticky/default_profile_images/default_profile_200x200.png"}
,
{"CreatedAt":"Wed Aug 17 16:19:20 +0000 2022","Text":"RT @OPLA_TECH: これは自分をインダクタだと思い込んでいるパインアメ https://t.co/IMSYT1nFY3","StatusId":"1559937936002797569","UserName":"Gada / ymtszw","UserProfileImageUrl":"https://pbs.twimg.com/profile_images/1520432647868391430/4b2AUYjC_normal.jpg","ExtendedEntitiesMediaUrls":"https://t.co/IMSYT1nFY3","ExtendedEntitiesMediaSourceUrls":"https://pbs.twimg.com/media/FaWqzSCUEAA_kSb.jpg","ExtendedEntitiesMediaTypes":"photo","ExtendedEntitiesMediaExpandedUrls":"https://twitter.com/OPLA_TECH/status/1559840648152223745/photo/1","Retweet":"TRUE","RetweetedStatusFullText":"これは自分をインダクタだと思い込んでいるパインアメ https://t.co/IMSYT1nFY3","RetweetedStatusId":"1559937936002797569","RetweetedStatusUserName":"おぷら技研","RetweetedStatusUserProfileImageUrl":"https://abs.twimg.com/sticky/default_profile_images/default_profile_200x200.png"}
,
{"CreatedAt":"Wed Aug 17 17:31:21 +0000 2022","Text":"RT @calmeryme: Deno を使った個人開発、最初は自力で諸々実装頑張ってたけどやっぱり npm パッケージ使いたくて Node.js に戻したことがあるのでこれは嬉しい","StatusId":"1559956057598099456","UserName":"Gada / ymtszw","UserProfileImageUrl":"https://pbs.twimg.com/profile_images/1520432647868391430/4b2AUYjC_normal.jpg","Retweet":"TRUE","RetweetedStatusFullText":"Deno を使った個人開発、最初は自力で諸々実装頑張ってたけどやっぱり npm パッケージ使いたくて Node.js に戻したことがあるのでこれは嬉しい","RetweetedStatusId":"1559956057598099456","RetweetedStatusUserName":"Calmery","RetweetedStatusUserProfileImageUrl":"https://abs.twimg.com/sticky/default_profile_images/default_profile_200x200.png"}
,
{"CreatedAt":"Thu Aug 18 09:46:50 +0000 2022","Text":"RT @kagilinn: @kuromitsu_ka 別にプログラミングしてなくても、Twitterしてるだけで新しい言語やフレームワークの情報が入ってきますし…\nそれで興味持ったらググる、ってやってるといつの間にか色々覚えてることになってる気がします","StatusId":"1560201546528239617","UserName":"Gada / ymtszw","UserProfileImageUrl":"https://pbs.twimg.com/profile_images/1520432647868391430/4b2AUYjC_normal.jpg","Retweet":"TRUE","RetweetedStatusFullText":"@kuromitsu_ka 別にプログラミングしてなくても、Twitterしてるだけで新しい言語やフレームワークの情報が入ってきますし…\nそれで興味持ったらググる、ってやってるといつの間にか色々覚えてることになってる気がします","RetweetedStatusId":"1560201546528239617","RetweetedStatusUserName":"かぎりん","RetweetedStatusUserProfileImageUrl":"https://abs.twimg.com/sticky/default_profile_images/default_profile_200x200.png"}
,
{"CreatedAt":"Thu Aug 18 10:56:13 +0000 2022","Text":"RT @gigazine: macOSと同等のエクスペリエンスと互換性を目指して開発されているオープンソースOS「ravynOS」\nhttps://t.co/svbmrseCJL","StatusId":"1560219008212668416","UserName":"Gada / ymtszw","UserProfileImageUrl":"https://pbs.twimg.com/profile_images/1520432647868391430/4b2AUYjC_normal.jpg","Retweet":"TRUE","RetweetedStatusFullText":"macOSと同等のエクスペリエンスと互換性を目指して開発されているオープンソースOS「ravynOS」\nhttps://t.co/svbmrseCJL","RetweetedStatusId":"1560219008212668416","RetweetedStatusUserName":"GIGAZINE(ギガジン)","RetweetedStatusUserProfileImageUrl":"https://abs.twimg.com/sticky/default_profile_images/default_profile_200x200.png"}
,
{"CreatedAt":"Thu Aug 18 11:00:49 +0000 2022","Text":"RT @ohashimasaki: 「損保乃糸」（そんぽのいと）で検索すると結構出て来るな…\n驚き…","StatusId":"1560220165781958657","UserName":"Gada / ymtszw","UserProfileImageUrl":"https://pbs.twimg.com/profile_images/1520432647868391430/4b2AUYjC_normal.jpg","Retweet":"TRUE","RetweetedStatusFullText":"「損保乃糸」（そんぽのいと）で検索すると結構出て来るな…\n驚き…","RetweetedStatusId":"1560220165781958657","RetweetedStatusUserName":"masaki ohashi","RetweetedStatusUserProfileImageUrl":"https://abs.twimg.com/sticky/default_profile_images/default_profile_200x200.png"}
,
{"CreatedAt":"Thu Aug 18 11:03:17 +0000 2022","Text":"RT @reactive_dude: When devs push to prod on Friday night https://t.co/BKBYcJpL7X","StatusId":"1560220784483741696","UserName":"Gada / ymtszw","UserProfileImageUrl":"https://pbs.twimg.com/profile_images/1520432647868391430/4b2AUYjC_normal.jpg","ExtendedEntitiesMediaUrls":"https://t.co/BKBYcJpL7X","ExtendedEntitiesMediaSourceUrls":"https://pbs.twimg.com/ext_tw_video_thumb/1559903225322655746/pu/img/sxqlTOpuMYzI0klX.jpg","ExtendedEntitiesMediaTypes":"video","ExtendedEntitiesMediaExpandedUrls":"https://twitter.com/reactive_dude/status/1559904011079270404/video/1","Retweet":"TRUE","RetweetedStatusFullText":"When devs push to prod on Friday night https://t.co/BKBYcJpL7X","RetweetedStatusId":"1560220784483741696","RetweetedStatusUserName":"Andrej ⚡️","RetweetedStatusUserProfileImageUrl":"https://abs.twimg.com/sticky/default_profile_images/default_profile_200x200.png"}
,
{"CreatedAt":"Thu Aug 18 11:05:28 +0000 2022","Text":"RT @inunokagayaki: https://t.co/SCZDDs8JwX","StatusId":"1560221334528933888","UserName":"Gada / ymtszw","UserProfileImageUrl":"https://pbs.twimg.com/profile_images/1520432647868391430/4b2AUYjC_normal.jpg","ExtendedEntitiesMediaUrls":"https://t.co/SCZDDs8JwX","ExtendedEntitiesMediaSourceUrls":"https://pbs.twimg.com/media/FacBYqEaMAIsCWy.jpg","ExtendedEntitiesMediaTypes":"photo","ExtendedEntitiesMediaExpandedUrls":"https://twitter.com/inunokagayaki/status/1560217333632991233/photo/1","Retweet":"TRUE","RetweetedStatusFullText":"https://t.co/SCZDDs8JwX","RetweetedStatusId":"1560221334528933888","RetweetedStatusUserName":"犬のかがやき","RetweetedStatusUserProfileImageUrl":"https://abs.twimg.com/sticky/default_profile_images/default_profile_200x200.png"}
]
