[
{"CreatedAt":"Mon Jan 26 09:47:52 +0000 2015","Text":"Avatarの変更は普通に強い気がする．いままで24s/180s=13%uptimeだったのが20s/90s=22%uptimeになるわけだから，結構なBuffだ．CD1.5minのUseTrinketで強いのがあったりすればかなり効く","StatusId":"559648911715860480","UserName":"Gada / ymtszw","UserProfileImageUrl":"https://pbs.twimg.com/profile_images/1520432647868391430/4b2AUYjC_normal.jpg","Retweet":"FALSE"}
,
{"CreatedAt":"Mon Jan 26 09:49:17 +0000 2015","Text":"Ravager，Dragon roarとはサイクルがマッチしないが，Shockwave（概ね），Stormbolt，Siegebreaker(!?)とはマッチする．ShiegebreakerはBuffされたから，FearとAEが絶対にいらないならワンチャンありうる","StatusId":"559649267686469633","UserName":"Gada / ymtszw","UserProfileImageUrl":"https://pbs.twimg.com/profile_images/1520432647868391430/4b2AUYjC_normal.jpg","Retweet":"FALSE"}
,
{"CreatedAt":"Mon Jan 26 09:51:58 +0000 2015","Text":"ArmsはCSが未だにあるから微妙なのかもしれないけど，Furyは関係ない．GladはHeroic StrikeでDoTを上乗せできる分Bloodbathのが強いかもしれないけど，math次第ではこちもありうる","StatusId":"559649942600302592","UserName":"Gada / ymtszw","UserProfileImageUrl":"https://pbs.twimg.com/profile_images/1520432647868391430/4b2AUYjC_normal.jpg","Retweet":"FALSE"}
,
{"CreatedAt":"Mon Jan 26 10:00:39 +0000 2015","Text":"Fish caught in Draenor are now automatically filleted.\nPlayers can now always catch enormous fish from pools, regardless of skill.","StatusId":"559652124993130497","UserName":"Gada / ymtszw","UserProfileImageUrl":"https://pbs.twimg.com/profile_images/1520432647868391430/4b2AUYjC_normal.jpg","Retweet":"FALSE"}
,
{"CreatedAt":"Mon Jan 26 10:02:35 +0000 2015","Text":"Fishスキルが意味を持ったから現状の仕様は別に良かったんだけど，まあ時代遅れではあった．Pool以外ではこれからもスキル依存なのかな．\n捌かなきゃいけないのは無意味だとは思った．","StatusId":"559652614418075652","UserName":"Gada / ymtszw","UserProfileImageUrl":"https://pbs.twimg.com/profile_images/1520432647868391430/4b2AUYjC_normal.jpg","Retweet":"FALSE"}
,
{"CreatedAt":"Mon Jan 26 10:05:14 +0000 2015","Text":"Ashranのドロップでもらえる消費アイテム（WandとかScroll）が全部廃止．残念でもないし当然．","StatusId":"559653280943321089","UserName":"Gada / ymtszw","UserProfileImageUrl":"https://pbs.twimg.com/profile_images/1520432647868391430/4b2AUYjC_normal.jpg","Retweet":"FALSE"}
,
{"CreatedAt":"Mon Jan 26 10:12:04 +0000 2015","Text":"Garrison池で呼べるレアMurlocの200ルアードロップ率が下げられる．在庫を作っておくかな．","StatusId":"559655001220333568","UserName":"Gada / ymtszw","UserProfileImageUrl":"https://pbs.twimg.com/profile_images/1520432647868391430/4b2AUYjC_normal.jpg","Retweet":"FALSE"}
,
{"CreatedAt":"Mon Jan 26 10:13:48 +0000 2015","Text":"Alch建物のフォロワーから，自分専用のポーションがタダで貰えるようになる．","StatusId":"559655434311577600","UserName":"Gada / ymtszw","UserProfileImageUrl":"https://pbs.twimg.com/profile_images/1520432647868391430/4b2AUYjC_normal.jpg","Retweet":"FALSE"}
,
{"CreatedAt":"Mon Jan 26 10:14:11 +0000 2015","Text":"DPSpotがもらえるなら美味しいな","StatusId":"559655532370219008","UserName":"Gada / ymtszw","UserProfileImageUrl":"https://pbs.twimg.com/profile_images/1520432647868391430/4b2AUYjC_normal.jpg","Retweet":"FALSE"}
]
