[
{"CreatedAt":"Mon Jun 01 07:03:28 +0000 2020","Text":"Google翻訳に音声入力オプションがあるんですが、これに英語で話しかけると面白いですね","StatusId":"1267351037960089601","UserName":"Gada / ymtszw","UserProfileImageUrl":"https://pbs.twimg.com/profile_images/1520432647868391430/4b2AUYjC_normal.jpg","Retweet":"FALSE"}
,
{"CreatedAt":"Mon Jun 01 07:13:42 +0000 2020","Text":"音節数がある程度多いほうが正しく認識されやすい（短い1単語とかはかえってダメ）なんだけど、まあここらへんは結構前から傾向変わってない。\nでも語彙はまあまあ増えている感触","StatusId":"1267353613212413956","UserName":"Gada / ymtszw","UserProfileImageUrl":"https://pbs.twimg.com/profile_images/1520432647868391430/4b2AUYjC_normal.jpg","InReplyToStatusId":"1267351037960089601","InReplyToUserId":"352840258","Retweet":"FALSE"}
]
