[
{"CreatedAt":"Fri Jul 05 22:51:36 +0000 2019","Text":"永遠に選択するタイミングが訪れない季節になってしまった","StatusId":"1147276872037744640","UserName":"Gada / ymtszw","UserProfileImageUrl":"https://pbs.twimg.com/profile_images/1520432647868391430/4b2AUYjC_normal.jpg","Retweet":"FALSE"}
,
{"CreatedAt":"Fri Jul 05 23:35:45 +0000 2019","Text":"@Ndanka @kazachino_wow 後半は意外とパターンが見えるのでひたすらだるいだけのやつ","StatusId":"1147287985215295488","UserName":"Gada / ymtszw","UserProfileImageUrl":"https://pbs.twimg.com/profile_images/1520432647868391430/4b2AUYjC_normal.jpg","Retweet":"FALSE"}
,
{"CreatedAt":"Sat Jul 06 12:45:44 +0000 2019","Text":"RT @obIiS11KGpxvVdM: 「夜早めに寝たら、朝早く起きれる」\nっていう法則に、26歳になってやっと気付いた件","StatusId":"1147486789805830144","UserName":"Gada / ymtszw","UserProfileImageUrl":"https://pbs.twimg.com/profile_images/1520432647868391430/4b2AUYjC_normal.jpg","Retweet":"TRUE","RetweetedStatusFullText":"「夜早めに寝たら、朝早く起きれる」\nっていう法則に、26歳になってやっと気付いた件","RetweetedStatusId":"1147486789805830144","RetweetedStatusUserName":"obIiS11KGpxvVdM","RetweetedStatusUserProfileImageUrl":"https://abs.twimg.com/sticky/default_profile_images/default_profile_200x200.png"}
,
{"CreatedAt":"Sat Jul 06 13:00:54 +0000 2019","Text":"カワイ・レナード、Clippersか。結構見ることになりそうだ","StatusId":"1147490607817883648","UserName":"Gada / ymtszw","UserProfileImageUrl":"https://pbs.twimg.com/profile_images/1520432647868391430/4b2AUYjC_normal.jpg","Retweet":"FALSE"}
]
