[
{"CreatedAt":"Thu Jul 20 17:01:12 +0000 2017","Text":"もこっちハーレム要員増やし過ぎだぞ","StatusId":"888081368596402178","UserName":"Gada / ymtszw","UserProfileImageUrl":"https://pbs.twimg.com/profile_images/1520432647868391430/4b2AUYjC_normal.jpg","Retweet":"FALSE"}
,
{"CreatedAt":"Thu Jul 20 20:15:25 +0000 2017","Text":"RT @Hearthhead: The Lich King has ordered his minions to commence Icecrown Citadel tours. https://t.co/SXTvJUAh6e https://t.co/7QPRPajM4V","StatusId":"888130242174308353","UserName":"Gada / ymtszw","UserProfileImageUrl":"https://pbs.twimg.com/profile_images/1520432647868391430/4b2AUYjC_normal.jpg","ExtendedEntitiesMediaUrls":"https://t.co/7QPRPajM4V","ExtendedEntitiesMediaSourceUrls":"https://pbs.twimg.com/media/DFMc385V0AE6N-Y.jpg","ExtendedEntitiesMediaTypes":"photo","ExtendedEntitiesMediaExpandedUrls":"https://twitter.com/Hearthhead/status/888085493216190465/photo/1","Retweet":"TRUE","RetweetedStatusFullText":"The Lich King has ordered his minions to commence Icecrown Citadel tours. https://t.co/SXTvJUAh6e https://t.co/7QPRPajM4V","RetweetedStatusId":"888130242174308353","RetweetedStatusUserName":"Hearthhead","RetweetedStatusUserProfileImageUrl":"https://abs.twimg.com/sticky/default_profile_images/default_profile_200x200.png"}
]
