[
{"CreatedAt":"Fri Oct 04 16:23:34 +0000 2013","Text":"久々に帰宅してぶっ倒れる程度に飲んだ。ワインは結構来る","StatusId":"386164701593219072","UserName":"Gada / ymtszw","UserProfileImageUrl":"https://pbs.twimg.com/profile_images/1520432647868391430/4b2AUYjC_normal.jpg","Retweet":"FALSE"}
,
{"CreatedAt":"Fri Oct 04 16:46:36 +0000 2013","Text":"@kusunoki666 軽く寝て休んだら目が冴えてきたからゲームするっす（照","StatusId":"386170501497778177","UserName":"Gada / ymtszw","UserProfileImageUrl":"https://pbs.twimg.com/profile_images/1520432647868391430/4b2AUYjC_normal.jpg","Retweet":"FALSE"}
,
{"CreatedAt":"Fri Oct 04 16:56:10 +0000 2013","Text":"夕立いるかなあと思ってチェックしてみたけど案の定いなかったよね。駆逐は平気で改装・解体に回してしまうから欲しいと思った時にいない","StatusId":"386172908323618817","UserName":"Gada / ymtszw","UserProfileImageUrl":"https://pbs.twimg.com/profile_images/1520432647868391430/4b2AUYjC_normal.jpg","Retweet":"FALSE"}
,
{"CreatedAt":"Fri Oct 04 16:57:14 +0000 2013","Text":"同じ理由で響もいないね","StatusId":"386173176763265025","UserName":"Gada / ymtszw","UserProfileImageUrl":"https://pbs.twimg.com/profile_images/1520432647868391430/4b2AUYjC_normal.jpg","Retweet":"FALSE"}
,
{"CreatedAt":"Fri Oct 04 17:37:25 +0000 2013","Text":"夜戦強制で5-3の運マップ具合やばいな","StatusId":"386183286474555392","UserName":"Gada / ymtszw","UserProfileImageUrl":"https://pbs.twimg.com/profile_images/1520432647868391430/4b2AUYjC_normal.jpg","Retweet":"FALSE"}
,
{"CreatedAt":"Sat Oct 05 09:19:14 +0000 2013","Text":"修理に回す鋼もない状態で5-3を回し続ける","StatusId":"386420302902620160","UserName":"Gada / ymtszw","UserProfileImageUrl":"https://pbs.twimg.com/profile_images/1520432647868391430/4b2AUYjC_normal.jpg","Retweet":"FALSE"}
,
{"CreatedAt":"Sat Oct 05 12:21:32 +0000 2013","Text":"@akisaya_mkd @hal_tvvitter PalとLockが強かった","StatusId":"386466181407727616","UserName":"Gada / ymtszw","UserProfileImageUrl":"https://pbs.twimg.com/profile_images/1520432647868391430/4b2AUYjC_normal.jpg","Retweet":"FALSE"}
,
{"CreatedAt":"Sat Oct 05 12:38:08 +0000 2013","Text":"ちょっと遅れるのでinvしててください #mkd_wow","StatusId":"386470359995670529","UserName":"Gada / ymtszw","UserProfileImageUrl":"https://pbs.twimg.com/profile_images/1520432647868391430/4b2AUYjC_normal.jpg","Retweet":"FALSE"}
]
