[
{"CreatedAt":"Sat Feb 03 15:39:03 +0000 2018","Text":"ちょっとオーバーしてHeroic全部。もう少し慣れれば2Hに収まるかな。レジェTrinketは見えず。\nやっぱ崩れがちなのはCovenか\nhttps://t.co/71RtL5q6lE\n#ut_wow","StatusId":"959813492004945920","UserName":"Gada / ymtszw","UserProfileImageUrl":"https://pbs.twimg.com/profile_images/1520432647868391430/4b2AUYjC_normal.jpg","EntitiesUrlsUrls":"https://t.co/71RtL5q6lE","EntitiesUrlsExpandedUrls":"https://www.warcraftlogs.com/reports/qYwV91XA8fZk7N4F/","Retweet":"FALSE"}
,
{"CreatedAt":"Sat Feb 03 18:00:50 +0000 2018","Text":"@mapi 元タスクが何らかの成果物を吐くのであれば、元タスクとは別に成果物の存在確認をするタスクを別で用意して、そちらで失敗を検知してアラートするという手法が比較的安定します。成果物を吐く必要がないタスクでも、成功したら終了直前に空ファイルを吐くようにすれば同じことができます。","StatusId":"959849172743540737","UserName":"Gada / ymtszw","UserProfileImageUrl":"https://pbs.twimg.com/profile_images/1520432647868391430/4b2AUYjC_normal.jpg","InReplyToStatusId":"959848197253251072","InReplyToUserId":"8243392","Retweet":"FALSE"}
,
{"CreatedAt":"Sat Feb 03 18:03:50 +0000 2018","Text":"@mapi この手法のいいところとして、「元タスクはこの時刻には通常必ず終わってるはず」という時刻に成果物チェックタスクを仕込めば、元タスクのほうが何らかの理由で徐々に時間がかかるようになっていた、みたいなありがちな現象も捕捉できる","StatusId":"959849927546347520","UserName":"Gada / ymtszw","UserProfileImageUrl":"https://pbs.twimg.com/profile_images/1520432647868391430/4b2AUYjC_normal.jpg","InReplyToStatusId":"959849172743540737","InReplyToUserId":"352840258","Retweet":"FALSE"}
,
{"CreatedAt":"Sat Feb 03 20:19:40 +0000 2018","Text":"コマンド一発でGNU Screenを複数paneで開く（ローカル開発時に複数のサーバプロセスを起動しつつそれぞれ別paneで分割表示する） - ymtszw - Scrapbox https://t.co/8jELy5pbj5","StatusId":"959884112923258880","UserName":"Gada / ymtszw","UserProfileImageUrl":"https://pbs.twimg.com/profile_images/1520432647868391430/4b2AUYjC_normal.jpg","EntitiesUrlsUrls":"https://t.co/8jELy5pbj5","EntitiesUrlsExpandedUrls":"https://scrapbox.io/ymtszw/%E3%82%B3%E3%83%9E%E3%83%B3%E3%83%89%E4%B8%80%E7%99%BA%E3%81%A7GNU_Screen%E3%82%92%E8%A4%87%E6%95%B0pane%E3%81%A7%E9%96%8B%E3%81%8F%EF%BC%88%E3%83%AD%E3%83%BC%E3%82%AB%E3%83%AB%E9%96%8B%E7%99%BA%E6%99%82%E3%81%AB%E8%A4%87%E6%95%B0%E3%81%AE%E3%82%B5%E3%83%BC%E3%83%90%E3%83%97%E3%83%AD%E3%82%BB%E3%82%B9%E3%82%92%E8%B5%B7%E5%8B%95%E3%81%97%E3%81%A4%E3%81%A4%E3%81%9D%E3%82%8C%E3%81%9E%E3%82%8C%E5%88%A5pane%E3%81%A7%E5%88%86%E5%89%B2%E8%A1%A8%E7%A4%BA%E3%81%99%E3%82%8B%EF%BC%89","Retweet":"FALSE"}
,
{"CreatedAt":"Sat Feb 03 20:20:06 +0000 2018","Text":"自分の環境ではすごく便利な小技を発見した https://t.co/3J60uhtjhX","StatusId":"959884218229653504","UserName":"Gada / ymtszw","UserProfileImageUrl":"https://pbs.twimg.com/profile_images/1520432647868391430/4b2AUYjC_normal.jpg","EntitiesUrlsUrls":"https://t.co/3J60uhtjhX","EntitiesUrlsExpandedUrls":"https://twitter.com/gada_twt/status/959884112923258880","Retweet":"FALSE"}
,
{"CreatedAt":"Sun Feb 04 06:36:36 +0000 2018","Text":"HEISHAにもHaskell製の商用プロダクトはあって稼働中だけど、Haskellエンジニア一切募集してないな。ごくたまにソースコードは読みに行く。","StatusId":"960039368961355777","UserName":"Gada / ymtszw","UserProfileImageUrl":"https://pbs.twimg.com/profile_images/1520432647868391430/4b2AUYjC_normal.jpg","Retweet":"FALSE"}
,
{"CreatedAt":"Sun Feb 04 06:44:00 +0000 2018","Text":"Firefoxのfor速度比較が遅すぎると思ったので試してみた on @Qiita https://t.co/LjYmzm9ssu\n\nhttps://t.co/qhlwWmsiL2って結構オーバーヘッドあるんだな。そしてFirefoxかなり速くなってる","StatusId":"960041230817099777","UserName":"Gada / ymtszw","UserProfileImageUrl":"https://pbs.twimg.com/profile_images/1520432647868391430/4b2AUYjC_normal.jpg","EntitiesUrlsUrls":"https://t.co/LjYmzm9ssu,https://t.co/qhlwWmsiL2","EntitiesUrlsExpandedUrls":"https://qiita.com/noxi515/items/12abcd18007a107f2bda,http://Array.prototype.map","Retweet":"FALSE"}
,
{"CreatedAt":"Sun Feb 04 06:47:49 +0000 2018","Text":"@Qiita \".map\"なんつーgTLDがいつのまにか提案されてたのか。。。","StatusId":"960042191040036864","UserName":"Gada / ymtszw","UserProfileImageUrl":"https://pbs.twimg.com/profile_images/1520432647868391430/4b2AUYjC_normal.jpg","InReplyToStatusId":"960041230817099777","InReplyToUserId":"352840258","Retweet":"FALSE"}
,
{"CreatedAt":"Sun Feb 04 07:03:43 +0000 2018","Text":"新幹線定期の価格調べてみたけど、特急券価格の上乗せ分は思ったより割引が効いてて、鈍行定期価格に1ヶ月で＋2万とかだった（東京・佐久平間の例）。\n鈍行定期代なら無条件で全額出る会社なら、新幹線通勤思ったより安くできちゃうな。もっと金かかると思ってた","StatusId":"960046193219846144","UserName":"Gada / ymtszw","UserProfileImageUrl":"https://pbs.twimg.com/profile_images/1520432647868391430/4b2AUYjC_normal.jpg","Retweet":"FALSE"}
,
{"CreatedAt":"Sun Feb 04 07:14:44 +0000 2018","Text":"RT @cutiesmegane: [2018/02/04 15:00] 眼鏡女子の画像をつぶやいています。 #めがねっ娘 #メガネっ娘 #眼鏡っ娘 https://t.co/sIPHOMK5nJ","StatusId":"960048962110504960","UserName":"Gada / ymtszw","UserProfileImageUrl":"https://pbs.twimg.com/profile_images/1520432647868391430/4b2AUYjC_normal.jpg","ExtendedEntitiesMediaUrls":"https://t.co/sIPHOMK5nJ","ExtendedEntitiesMediaSourceUrls":"https://pbs.twimg.com/media/DVK2WUMV4AAk0On.jpg","ExtendedEntitiesMediaTypes":"photo","ExtendedEntitiesMediaExpandedUrls":"https://twitter.com/cutiesmegane/status/960030167052595200/photo/1","Retweet":"TRUE","RetweetedStatusFullText":"[2018/02/04 15:00] 眼鏡女子の画像をつぶやいています。 #めがねっ娘 #メガネっ娘 #眼鏡っ娘 https://t.co/sIPHOMK5nJ","RetweetedStatusId":"960048962110504960","RetweetedStatusUserName":"眼鏡っ娘bot(めがねっ娘、メガネ女子)","RetweetedStatusUserProfileImageUrl":"https://res.cloudinary.com/du9b7ybxy/image/twitter_name/h_20,w_20,d_default_twitter_avatar.jpg/cutiesmegane.jpg"}
,
{"CreatedAt":"Sun Feb 04 09:46:51 +0000 2018","Text":"おもったよりilvl高くてHaste盛りの装備が手にはいらなくて、速足セットが164％より上がらない","StatusId":"960087243552473089","UserName":"Gada / ymtszw","UserProfileImageUrl":"https://pbs.twimg.com/profile_images/1520432647868391430/4b2AUYjC_normal.jpg","Retweet":"FALSE"}
]
